{
  "required": true,
  "package": "fi.dy.masa.malilib.mixin",
  "compatibilityLevel": "JAVA_21",
  "minVersion": "0.8",
  "client": [
    "IMixinDrawContext",
    "MixinClientConfigurationNetworkHandler",
    "MixinClientPlayNetworkHandler",
    "MixinDebugRenderer",
    "MixinDrawContext",
    "MixinHandledScreen",
    "MixinHorseEntity",
    "MixinInGameHud",
    "MixinIntegratedServer",
    "MixinKeyboard",
    "MixinMinecraftClient",
    "MixinMinecraftServer",
    "MixinMouse",
    "MixinParticleManager",
    "MixinPiglinEntity",
    "MixinSimpleInventory",
    "MixinWorldRenderer",
    "test.IMixinAbstractHorseEntity"
  ],
  "injectors": {
    "defaultRequire": 1
  }
}
